hero_base/__init__.py
hero_base/memory.py
hero_base/model.py
hero_base/state.py
hero_base/tool.py
tests/__init__.py
tests/state.py
hero_base-0.2.1.dist-info/METADATA
hero_base-0.2.1.dist-info/WHEEL
hero_base-0.2.1.dist-info/top_level.txt
hero_base-0.2.1.dist-info/RECORD
