Metadata-Version: 2.4
Name: hero-base
Version: 0.2.1
Summary: Add your description here
Home-page: https://github.com/baidu/hero-tools
Author: Baidu
Author-email: wangdejiang@baidu.com
Requires-Python: >=3.12
Requires-Dist: aiohttp>=3.12.15
Requires-Dist: dill>=0.4.0
Requires-Dist: pydantic>=2.11.7
Requires-Dist: setuptools>=80.9.0
Requires-Dist: twine>=6.1.0
Dynamic: author
Dynamic: author-email
Dynamic: home-page
Dynamic: requires-python
